nlpstats/__init__.py
nlpstats/version.py
nlpstats/correlations/__init__.py
nlpstats/correlations/bootstrap.py
nlpstats/correlations/correlations.py
nlpstats/correlations/fisher.py
nlpstats/correlations/permutation.py
nlpstats/correlations/resampling.py
nlpstats/correlations/williams.py
nlpstats-0.0.1.dist-info/LICENSE
nlpstats-0.0.1.dist-info/METADATA
nlpstats-0.0.1.dist-info/WHEEL
nlpstats-0.0.1.dist-info/top_level.txt
nlpstats-0.0.1.dist-info/RECORD
