Metadata-Version: 2.1
Name: nlpstats
Version: 0.0.1
Summary: A statistical toolbox for NLP
Home-page: https://github.com/danieldeutsch/nlpstats
Author: Daniel Deutsch
License: UNKNOWN
Platform: UNKNOWN
Requires-Python: >=3.7
License-File: LICENSE
Requires-Dist: numpy (>=1.20.0)
Requires-Dist: scipy
